sbase/__init__.py
sbase/__main__.py
sbase/steps.py
seleniumbase/__init__.py
seleniumbase/__main__.py
seleniumbase/__version__.py
seleniumbase/behave/__init__.py
seleniumbase/behave/behave_helper.py
seleniumbase/behave/behave_sb.py
seleniumbase/behave/steps.py
seleniumbase/common/__init__.py
seleniumbase/common/decorators.py
seleniumbase/common/encryption.py
seleniumbase/common/exceptions.py
seleniumbase/common/obfuscate.py
seleniumbase/common/unobfuscate.py
seleniumbase/config/__init__.py
seleniumbase/config/ad_block_list.py
seleniumbase/config/proxy_list.py
seleniumbase/config/settings.py
seleniumbase/console_scripts/__init__.py
seleniumbase/console_scripts/logo_helper.py
seleniumbase/console_scripts/rich_helper.py
seleniumbase/console_scripts/run.py
seleniumbase/console_scripts/sb_behave_gui.py
seleniumbase/console_scripts/sb_caseplans.py
seleniumbase/console_scripts/sb_commander.py
seleniumbase/console_scripts/sb_install.py
seleniumbase/console_scripts/sb_mkchart.py
seleniumbase/console_scripts/sb_mkdir.py
seleniumbase/console_scripts/sb_mkfile.py
seleniumbase/console_scripts/sb_mkpres.py
seleniumbase/console_scripts/sb_mkrec.py
seleniumbase/console_scripts/sb_objectify.py
seleniumbase/console_scripts/sb_print.py
seleniumbase/console_scripts/sb_recorder.py
seleniumbase/core/__init__.py
seleniumbase/core/application_manager.py
seleniumbase/core/browser_launcher.py
seleniumbase/core/capabilities_parser.py
seleniumbase/core/colored_traceback.py
seleniumbase/core/create_db_tables.sql
seleniumbase/core/detect_b_ver.py
seleniumbase/core/download_helper.py
seleniumbase/core/encoded_images.py
seleniumbase/core/jqc_helper.py
seleniumbase/core/log_helper.py
seleniumbase/core/mysql.py
seleniumbase/core/proxy_helper.py
seleniumbase/core/recorder_helper.py
seleniumbase/core/report_helper.py
seleniumbase/core/s3_manager.py
seleniumbase/core/sb_cdp.py
seleniumbase/core/sb_driver.py
seleniumbase/core/session_helper.py
seleniumbase/core/settings_parser.py
seleniumbase-4.45.10.dist-info/licenses/LICENSE
seleniumbase-4.45.10.dist-info/METADATA
seleniumbase-4.45.10.dist-info/WHEEL
seleniumbase-4.45.10.dist-info/entry_points.txt
seleniumbase-4.45.10.dist-info/top_level.txt
seleniumbase-4.45.10.dist-info/RECORD
