Metadata-Version: 2.4
Name: seleniumbase
Version: 4.45.10
Summary: A complete web automation framework for end-to-end testing.
Home-page: https://github.com/seleniumbase/SeleniumBase
Author: Michael Mintz
Author-email: mdmintz@gmail.com
Maintainer: Michael Mintz
License: MIT
Project-URL: Homepage, https://github.com/seleniumbase/SeleniumBase
Project-URL: Changelog, https://github.com/seleniumbase/SeleniumBase/releases
Project-URL: Download, https://pypi.org/project/seleniumbase/#files
Project-URL: Blog, https://seleniumbase.com/
Project-URL: Discord, https://discord.gg/EdhQTn3EyE
Project-URL: PyPI, https://pypi.org/project/seleniumbase/
Project-URL: Source, https://github.com/seleniumbase/SeleniumBase
Project-URL: Repository, https://github.com/seleniumbase/SeleniumBase
Project-URL: Documentation, https://seleniumbase.io/
Keywords: pytest,selenium,framework,automation,browser,testing,webdriver,seleniumbase,sbase,crawling,scraping
Platform: Windows
Platform: Linux
Platform: Mac OS-X
Classifier: Development Status :: 5 - Production/Stable
Classifier: Environment :: Console
Classifier: Environment :: MacOS X
Classifier: Environment :: Win32 (MS Windows)
Classifier: Environment :: Web Environment
Classifier: Framework :: Pytest
Classifier: Intended Audience :: Developers
Classifier: Intended Audience :: Information Technology
Classifier: Operating System :: MacOS :: MacOS X
Classifier: Operating System :: Microsoft :: Windows
Classifier: Operating System :: POSIX :: Linux
Classifier: Programming Language :: Python
Classifier: Programming Language :: Python :: 3
Classifier: Programming Language :: Python :: 3.9
Classifier: Programming Language :: Python :: 3.10
Classifier: Programming Language :: Python :: 3.11
Classifier: Programming Language :: Python :: 3.12
Classifier: Programming Language :: Python :: 3.13
Classifier: Programming Language :: Python :: 3.14
Classifier: Topic :: Internet
Classifier: Topic :: Internet :: WWW/HTTP :: Browsers
Classifier: Topic :: Scientific/Engineering
Classifier: Topic :: Scientific/Engineering :: Artificial Intelligence
Classifier: Topic :: Scientific/Engineering :: Image Processing
Classifier: Topic :: Scientific/Engineering :: Visualization
Classifier: Topic :: Software Development
Classifier: Topic :: Software Development :: Quality Assurance
Classifier: Topic :: Software Development :: Code Generators
Classifier: Topic :: Software Development :: Libraries
Classifier: Topic :: Software Development :: Libraries :: Application Frameworks
Classifier: Topic :: Software Development :: Libraries :: Python Modules
Classifier: Topic :: Software Development :: Testing
Classifier: Topic :: Software Development :: Testing :: Acceptance
Classifier: Topic :: Software Development :: Testing :: Traffic Generation
Classifier: Topic :: Utilities
Requires-Python: >=3.9
License-File: LICENSE
Requires-Dist: pip>=25.3
Requires-Dist: packaging>=25.0
Requires-Dist: setuptools~=70.2; python_version < "3.10"
Requires-Dist: setuptools>=80.9.0; python_version >= "3.10"
Requires-Dist: wheel>=0.45.1
Requires-Dist: attrs>=25.4.0
Requires-Dist: certifi>=2026.1.4
Requires-Dist: exceptiongroup>=1.3.1
Requires-Dist: websockets>=15.0.1
Requires-Dist: filelock~=3.19.1; python_version < "3.10"
Requires-Dist: filelock>=3.20.2; python_version >= "3.10"
Requires-Dist: fasteners>=0.20
Requires-Dist: mycdp>=1.3.2
Requires-Dist: pynose>=1.5.5
Requires-Dist: platformdirs~=4.4.0; python_version < "3.10"
Requires-Dist: platformdirs>=4.5.1; python_version >= "3.10"
Requires-Dist: typing-extensions>=4.15.0
Requires-Dist: sbvirtualdisplay>=1.4.0
Requires-Dist: MarkupSafe>=3.0.3
Requires-Dist: Jinja2>=3.1.6
Requires-Dist: six>=1.17.0
Requires-Dist: parse>=1.20.2
Requires-Dist: parse-type>=0.6.6
Requires-Dist: colorama>=0.4.6
Requires-Dist: pyyaml>=6.0.3
Requires-Dist: pygments>=2.19.2
Requires-Dist: pyreadline3>=3.5.4; platform_system == "Windows"
Requires-Dist: tabcompleter>=1.4.0
Requires-Dist: pdbp>=1.8.1
Requires-Dist: idna>=3.11
Requires-Dist: chardet==5.2.0
Requires-Dist: charset-normalizer<4,>=3.4.4
Requires-Dist: urllib3<2,>=1.26.20; python_version < "3.10"
Requires-Dist: urllib3<3,>=1.26.20; python_version >= "3.10"
Requires-Dist: requests~=2.32.5
Requires-Dist: sniffio==1.3.1
Requires-Dist: h11==0.16.0
Requires-Dist: outcome==1.3.0.post0
Requires-Dist: trio<1,>=0.31.0; python_version < "3.10"
Requires-Dist: trio<1,>=0.32.0; python_version >= "3.10"
Requires-Dist: trio-websocket~=0.12.2
Requires-Dist: wsproto==1.2.0; python_version < "3.10"
Requires-Dist: wsproto~=1.3.2; python_version >= "3.10"
Requires-Dist: websocket-client~=1.9.0
Requires-Dist: selenium==4.32.0; python_version < "3.10"
Requires-Dist: selenium==4.39.0; python_version >= "3.10"
Requires-Dist: cssselect==1.3.0
Requires-Dist: nest-asyncio==1.6.0
Requires-Dist: sortedcontainers==2.4.0
Requires-Dist: execnet==2.1.1; python_version < "3.10"
Requires-Dist: execnet==2.1.2; python_version >= "3.10"
Requires-Dist: iniconfig==2.1.0; python_version < "3.10"
Requires-Dist: iniconfig==2.3.0; python_version >= "3.10"
Requires-Dist: pluggy==1.6.0
Requires-Dist: pytest==8.4.2; python_version < "3.11"
Requires-Dist: pytest==9.0.2; python_version >= "3.11"
Requires-Dist: pytest-html==4.0.2
Requires-Dist: pytest-metadata==3.1.1
Requires-Dist: pytest-ordering==0.6
Requires-Dist: pytest-rerunfailures==16.0.1; python_version < "3.10"
Requires-Dist: pytest-rerunfailures==16.1; python_version >= "3.10"
Requires-Dist: pytest-xdist==3.8.0
Requires-Dist: parameterized==0.9.0
Requires-Dist: behave==1.2.6
Requires-Dist: soupsieve~=2.8.1
Requires-Dist: beautifulsoup4~=4.14.3
Requires-Dist: pyotp==2.9.0
Requires-Dist: python-xlib==0.33; platform_system == "Linux"
Requires-Dist: PyAutoGUI>=0.9.54; platform_system == "Linux"
Requires-Dist: markdown-it-py==3.0.0; python_version < "3.10"
Requires-Dist: markdown-it-py==4.0.0; python_version >= "3.10"
Requires-Dist: mdurl==0.1.2
Requires-Dist: rich<15,>=14.2.0
Provides-Extra: allure
Requires-Dist: allure-pytest>=2.13.5; extra == "allure"
Requires-Dist: allure-python-commons>=2.13.5; extra == "allure"
Requires-Dist: allure-behave>=2.13.5; extra == "allure"
Provides-Extra: coverage
Requires-Dist: coverage>=7.10.7; python_version < "3.10" and extra == "coverage"
Requires-Dist: coverage>=7.13.1; python_version >= "3.10" and extra == "coverage"
Requires-Dist: pytest-cov>=7.0.0; extra == "coverage"
Provides-Extra: flake8
Requires-Dist: flake8==7.3.0; extra == "flake8"
Requires-Dist: mccabe==0.7.0; extra == "flake8"
Requires-Dist: pyflakes==3.4.0; extra == "flake8"
Requires-Dist: pycodestyle==2.14.0; extra == "flake8"
Provides-Extra: ipdb
Requires-Dist: ipdb==0.13.13; extra == "ipdb"
Requires-Dist: ipython==7.34.0; extra == "ipdb"
Provides-Extra: mss
Requires-Dist: mss==10.1.0; extra == "mss"
Provides-Extra: pdfminer
Requires-Dist: pdfminer.six==20251107; python_version < "3.10" and extra == "pdfminer"
Requires-Dist: pdfminer.six==20260107; python_version >= "3.10" and extra == "pdfminer"
Requires-Dist: cryptography==46.0.3; extra == "pdfminer"
Requires-Dist: cffi==2.0.0; extra == "pdfminer"
Requires-Dist: pycparser==2.23; extra == "pdfminer"
Provides-Extra: pillow
Requires-Dist: Pillow>=11.3.0; python_version < "3.10" and extra == "pillow"
Requires-Dist: Pillow>=12.1.0; python_version >= "3.10" and extra == "pillow"
Provides-Extra: pip-system-certs
Requires-Dist: pip-system-certs==4.0; platform_system == "Windows" and extra == "pip-system-certs"
Provides-Extra: proxy
Requires-Dist: proxy.py==2.4.3; extra == "proxy"
Provides-Extra: playwright
Requires-Dist: playwright>=1.56.0; extra == "playwright"
Provides-Extra: psutil
Requires-Dist: psutil>=7.1.3; extra == "psutil"
Provides-Extra: pyautogui
Requires-Dist: PyAutoGUI>=0.9.54; platform_system != "Linux" and extra == "pyautogui"
Provides-Extra: selenium-stealth
Requires-Dist: selenium-stealth==1.0.6; extra == "selenium-stealth"
Provides-Extra: selenium-wire
Requires-Dist: selenium-wire==5.1.0; extra == "selenium-wire"
Requires-Dist: pyOpenSSL>=24.2.1; extra == "selenium-wire"
Requires-Dist: pyparsing>=3.1.4; extra == "selenium-wire"
Requires-Dist: Brotli==1.1.0; extra == "selenium-wire"
Requires-Dist: blinker==1.7.0; extra == "selenium-wire"
Requires-Dist: h2==4.1.0; extra == "selenium-wire"
Requires-Dist: hpack==4.0.0; extra == "selenium-wire"
Requires-Dist: hyperframe==6.0.1; extra == "selenium-wire"
Requires-Dist: kaitaistruct==0.10; extra == "selenium-wire"
Requires-Dist: pyasn1==0.6.1; extra == "selenium-wire"
Requires-Dist: zstandard>=0.23.0; extra == "selenium-wire"
Dynamic: author
Dynamic: author-email
Dynamic: classifier
Dynamic: home-page
Dynamic: keywords
Dynamic: license
Dynamic: license-file
Dynamic: maintainer
Dynamic: platform
Dynamic: provides-extra
Dynamic: requires-dist
Dynamic: requires-python
Dynamic: summary
